processfamily/__init__.py
processfamily/_winprocess_ctypes.py
processfamily/ctypes_prctl.py
processfamily/processes.py
processfamily/test_prctl.py
processfamily/test_processfamily.py
processfamily/threads.py
processfamily/win32Popen.py
processfamily/test/ChildProcess.py
processfamily/test/Config.py
processfamily/test/ExeBuilder.py
processfamily/test/FunkyWebServer.py
processfamily/test/ParentProcess.py
processfamily/test/Win32Service.py
processfamily/test/__init__.py
processfamily/test/parent_launcher.py
processfamily-0.8.dist-info/LICENSE
processfamily-0.8.dist-info/METADATA
processfamily-0.8.dist-info/WHEEL
processfamily-0.8.dist-info/top_level.txt
processfamily-0.8.dist-info/RECORD
