Metadata-Version: 2.1
Name: processfamily
Version: 0.8
Summary: A library for launching, maintaining, and terminating a family of long-lived python child processes on Windows and Unices.
Home-page: http://www.j5int.com/
Author: j5 International
Author-email: support@j5int.com
License: Apache License, Version 2.0
Platform: UNKNOWN
Classifier: Development Status :: 3 - Alpha
Classifier: License :: OSI Approved :: Apache Software License
Classifier: Environment :: Web Environment
Classifier: Intended Audience :: Developers
Classifier: Operating System :: OS Independent
Classifier: Programming Language :: Python
Classifier: Topic :: Software Development :: Libraries :: Python Modules
Requires-Dist: json-rpc
Requires-Dist: affinity
Provides-Extra: tests
Requires-Dist: nose ; extra == 'tests'
Requires-Dist: requests ; extra == 'tests'
